{
  "main": {
    "id": "f2f0e9e200819a45",
    "type": "split",
    "children": [
      {
        "id": "b3e94fa80467c2e1",
        "type": "tabs",
        "children": [
          {
            "id": "de0aa3f1a4fed1be",
            "type": "leaf",
            "state": {
              "type": "markdown",
              "state": {
                "file": "个人项目/企业微信机器人.md",
                "mode": "source",
                "source": false
              }
            }
          }
        ]
      }
    ],
    "direction": "vertical"
  },
  "left": {
    "id": "e79887417a1666f0",
    "type": "split",
    "children": [
      {
        "id": "b912d1680f9227aa",
        "type": "tabs",
        "children": [
          {
            "id": "c6a768f226b1fe6c",
            "type": "leaf",
            "state": {
              "type": "file-explorer",
              "state": {
                "sortOrder": "alphabetical"
              }
            }
          },
          {
            "id": "24d0e6198c79dea1",
            "type": "leaf",
            "state": {
              "type": "search",
              "state": {
                "query": "简历",
                "matchingCase": false,
                "explainSearch": false,
                "collapseAll": false,
                "extraContext": false,
                "sortOrder": "alphabetical"
              }
            }
          },
          {
            "id": "896a3bc86400cc32",
            "type": "leaf",
            "state": {
              "type": "bookmarks",
              "state": {}
            }
          }
        ]
      }
    ],
    "direction": "horizontal",
    "width": 300
  },
  "right": {
    "id": "7f30979e2d155193",
    "type": "split",
    "children": [
      {
        "id": "1b3f70ee0679960f",
        "type": "tabs",
        "children": [
          {
            "id": "778c354afd445987",
            "type": "leaf",
            "state": {
              "type": "backlink",
              "state": {
                "file": "个人项目/企业微信机器人.md",
                "collapseAll": true,
                "extraContext": false,
                "sortOrder": "alphabetical",
                "showSearch": false,
                "searchQuery": "",
                "backlinkCollapsed": false,
                "unlinkedCollapsed": true
              }
            }
          },
          {
            "id": "03f98c20cb9a8c8a",
            "type": "leaf",
            "state": {
              "type": "outgoing-link",
              "state": {
                "file": "个人项目/企业微信机器人.md",
                "linksCollapsed": false,
                "unlinkedCollapsed": true
              }
            }
          },
          {
            "id": "299680305761abf8",
            "type": "leaf",
            "state": {
              "type": "tag",
              "state": {
                "sortOrder": "frequency",
                "useHierarchy": true
              }
            }
          },
          {
            "id": "02410dbffdebd548",
            "type": "leaf",
            "state": {
              "type": "outline",
              "state": {
                "file": "个人项目/企业微信机器人.md"
              }
            }
          }
        ],
        "currentTab": 3
      }
    ],
    "direction": "horizontal",
    "width": 277.5
  },
  "left-ribbon": {
    "hiddenItems": {
      "switcher:打开快速切换": false,
      "graph:查看关系图谱": false,
      "canvas:新建白板": false,
      "daily-notes:打开/创建今天的日记": false,
      "templates:插入模板": false,
      "command-palette:打开命令面板": false,
      "templater-obsidian:Templater": false
    }
  },
  "active": "de0aa3f1a4fed1be",
  "lastOpenFiles": [
    "个人项目/我的博客支持服务.md",
    "个人项目/企业微信机器人.md",
    "个人项目/开发一个ops的新客户端.md",
    "个人项目/开发一个带缓存的代理.md",
    "个人项目/计算贝塞尔曲线.md",
    "个人项目/创建MergeRequest的CLI工具.md",
    "个人项目/博客在线编辑器.md",
    "old/前端/fetch与axios.md",
    "old/前端/组件化.md",
    "old/前端/网站的兼容性.md",
    "old/面试/_index.md",
    "old/大杂烩/_index.md",
    "个人项目/_index.md",
    "小功能/_index.md",
    "小功能/调试proxy对象.md",
    "小功能/将emoji表情作为网站的favicon.md",
    "小功能/用html字符串生成dom元素.md",
    "小功能/IOS的固定列头滚动效果.md",
    "小功能/Java执行shell命令.md",
    "小功能/Table固定列头和行头.md",
    "old/大杂烩/笔记.md",
    "old/大杂烩/博客分类.md",
    "old/大杂烩",
    "技术知识点/_index.md",
    "技术知识点/设计模式.md",
    "技术知识点/ES6/箭头函数.md",
    "技术知识点/JS",
    "技术知识点/语义化标签.md",
    "技术知识点/ES6/未命名",
    "技术知识点/工程化",
    "技术知识点/CSS",
    "技术知识点/ES6",
    "技能/未命名",
    "技术知识点/浏览器与网络协议",
    "优化",
    "优化/授课项目首屏加载慢/优化-后.jpg",
    "优化/授课项目首屏加载慢/优化-代码.png",
    "优化/授课项目首屏加载慢/优化-前.jpg",
    "优化/授课项目首屏加载慢/优化-后2.jpg",
    "优化/授课项目首屏加载慢",
    "old/技术笔记/electron/Pasted image 20240407132410.png",
    "old/面试/怎么写简历/Pasted image 20240406230726.png",
    "附件/Pasted image 20240402202036.jpg",
    "附件/Pasted image 20240402201217.jpg",
    "附件/箭头函数1.png",
    "附件/285729db06404505887b554c12d4c230~tplv-k3u1fbpfcp-zoom-in-crop-mark_1512_0_0_0.webp"
  ]
}